{"_1":{"0":"banking","1":"business","2":"clinic (including dentist)","3":"dress code (booking and buying)","4":"emergency","5":"extracurricular training camp","6":"financial agency","7":"food (including takeaway)","8":"hospital (including health care)","9":"housekeeping and property management","10":"housing (including rental)","11":"job","12":"legal agency","13":"none","14":"private","15":"school","16":"traveling"},"_2":{"0":1988,"1":200,"2":170,"3":164,"4":192,"5":192,"6":179,"7":186,"8":186,"9":2747,"10":173,"11":175,"12":168,"13":169,"14":341,"15":189,"16":181}}